MANIFEST.in
README.md
pypi_description.rst
setup.py
jsonesque/__init__.py
jsonesque/process.py
jsonesque.egg-info/PKG-INFO
jsonesque.egg-info/SOURCES.txt
jsonesque.egg-info/dependency_links.txt
jsonesque.egg-info/top_level.txt
jsonesque/tests/__init__.py
jsonesque/tests/process_test.py