Metadata-Version: 1.1
Name: jsonesque
Version: 0.1.1
Summary: Normalise and minify JSON-like strings into valid JSON
Home-page: https://github.com/okdana/jsonesque/
Author: dana geier
Author-email: dana@dana.is
License: MIT
Keywords: json,json-like,comments,minify
Platform: UNKNOWN
Classifier: License :: OSI Approved :: MIT License
Classifier: Programming Language :: Python :: 2
Classifier: Programming Language :: Python :: 3
Classifier: Operating System :: OS Independent
Classifier: Intended Audience :: Developers
Classifier: Topic :: Software Development :: Libraries :: Python Modules
Classifier: Topic :: Software Development :: Pre-processors
Classifier: Topic :: Text Processing :: Filters
Classifier: Topic :: Utilities
